syncausalimpact/__init__.py
syncausalimpact/causal_impact.py
syncausalimpact-0.1.1.dist-info/METADATA
syncausalimpact-0.1.1.dist-info/WHEEL
syncausalimpact-0.1.1.dist-info/top_level.txt
syncausalimpact-0.1.1.dist-info/RECORD
