Metadata-Version: 2.1
Name: syncausalimpact
Version: 0.1.1
Summary: Python package for Geo-Matched Causal Impact (python wrapped version of R code)
Home-page: 
Author: Henry Dalgleish
Author-email: hwpdalgleish@gmail.com
Classifier: Programming Language :: Python :: 3
Classifier: License :: OSI Approved :: MIT License
Classifier: Operating System :: OS Independent
Requires-Python: >=3.8
Requires-Dist: pandas
Requires-Dist: numpy
Requires-Dist: seaborn
Requires-Dist: matplotlib
Requires-Dist: rpy2
Requires-Dist: statsmodels
Requires-Dist: scipy
Requires-Dist: python-dateutil
